[
  {
    "nom": "Angular",
    "icone": {
      "id": 19,
      "nom": "Angular.svg",
      "dossier": "technos",
      "url": null
    }
  },
  {
    "nom": "Java",
    "icone": {
      "id": 20,
      "nom": "Java.svg",
      "dossier": "technos",
      "url": null
    }
  },
  {
    "nom": "Spring",
    "icone": {
      "id": 21,
      "nom": "Spring.svg",
      "dossier": "technos",
      "url": null
    }
  },
  {
    "nom": "PostgreSQL",
    "icone": {
      "id": 22,
      "nom": "PostgreSQL.svg",
      "dossier": "technos",
      "url": null
    }
  },
  {
    "nom": "Linux",
    "icone": {
      "id": 23,
      "nom": "Linux.svg",
      "dossier": "technos",
      "url": null
    }
  }
]
